pytest_httpx_blockage/__init__.py
pytest_httpx_blockage/blockage.py
pytest_httpx_blockage/contextvar.py
pytest_httpx_blockage/exceptions.py
pytest_httpx_blockage/plugin.py
pytest_httpx_blockage/py.typed
pytest_httpx_blockage-0.0.8.dist-info/LICENSE
pytest_httpx_blockage-0.0.8.dist-info/METADATA
pytest_httpx_blockage-0.0.8.dist-info/WHEEL
pytest_httpx_blockage-0.0.8.dist-info/entry_points.txt
pytest_httpx_blockage-0.0.8.dist-info/top_level.txt
pytest_httpx_blockage-0.0.8.dist-info/zip-safe
pytest_httpx_blockage-0.0.8.dist-info/RECORD
