Metadata-Version: 2.1
Name: pytest-httpx-blockage
Version: 0.0.8
Summary: Disable httpx requests during a test run
Home-page: https://github.com/SlavaSkvortsov/pytest-httpx-blockage
Author: Slava Skvortsov
Classifier: Framework :: Pytest
Classifier: Environment :: Web Environment
Classifier: Intended Audience :: Developers
Classifier: License :: OSI Approved :: MIT License
Classifier: Operating System :: OS Independent
Classifier: Programming Language :: Python
Classifier: Programming Language :: Python :: 3
Classifier: Programming Language :: Python :: 3 :: Only
Classifier: Programming Language :: Python :: 3.8
Classifier: Programming Language :: Python :: 3.9
Classifier: Topic :: Internet :: WWW/HTTP
Classifier: Topic :: Software Development :: Libraries :: Python Modules
License-File: LICENSE
Requires-Dist: httpx (>=0.23.3)
Requires-Dist: pytest (>=7.2.1)
